nextlayer/sdk/__init__.py
nextlayer/sdk/__init__.pye
nextlayer/sdk/auth.py
nextlayer/sdk/auth_httpx.py
nextlayer/sdk/errors.py
nextlayer_sdk_python-1.0.2.dist-info/METADATA
nextlayer_sdk_python-1.0.2.dist-info/WHEEL
nextlayer_sdk_python-1.0.2.dist-info/entry_points.txt
nextlayer_sdk_python-1.0.2.dist-info/RECORD
