Metadata-Version: 2.3
Name: nextlayer-sdk-python
Version: 1.0.2
Summary: Client utilities to interact with next layer public APIs
Author: Wolfgang Powisch
Author-email: wolfgang.powisch@nextlayer.at
Requires-Python: >=3.11,<4.0
Classifier: Operating System :: OS Independent
Classifier: Operating System :: POSIX :: Linux
Classifier: Programming Language :: Python :: 3
Classifier: Programming Language :: Python :: 3.11
Classifier: Programming Language :: Python :: 3.12
Classifier: Programming Language :: Python :: 3.13
Requires-Dist: PyYAML (>=6.0,<7.0)
Requires-Dist: pydantic (>=2.10.6,<3.0.0)
Requires-Dist: pyjwt (>=2.10.1,<3.0.0)
Requires-Dist: python-keycloak (>=3.0.0,<4.0.0)
